<annotation>
	<folder>egg_new_compressed</folder>
	<filename>image_63.jpg</filename>
	<path>D:\egg_new_compressed\image_63.jpg</path>
	<source>
		<database>Unknown</database>
	</source>
	<size>
		<width>800</width>
		<height>450</height>
		<depth>3</depth>
	</size>
	<segmented>0</segmented>
	<object>
		<name>eggs</name>
		<pose>Unspecified</pose>
		<truncated>1</truncated>
		<difficult>0</difficult>
		<bndbox>
			<xmin>672</xmin>
			<ymin>192</ymin>
			<xmax>800</xmax>
			<ymax>338</ymax>
		</bndbox>
	</object>
	<object>
		<name>eggs</name>
		<pose>Unspecified</pose>
		<truncated>0</truncated>
		<difficult>0</difficult>
		<bndbox>
			<xmin>33</xmin>
			<ymin>156</ymin>
			<xmax>80</xmax>
			<ymax>205</ymax>
		</bndbox>
	</object>
</annotation>
